edudat/__init__.py
edudat/data_loader.py
edudat-0.3.dist-info/METADATA
edudat-0.3.dist-info/WHEEL
edudat-0.3.dist-info/top_level.txt
edudat-0.3.dist-info/RECORD
